python_mscl/__init__.py
python_mscl/_mscl.so
python_mscl/mscl.py
python_mscl/py.typed
python_mscl-67.1.0.0.dist-info/METADATA
python_mscl-67.1.0.0.dist-info/WHEEL
python_mscl-67.1.0.0.dist-info/licenses/LICENSE
python_mscl-67.1.0.0.dist-info/RECORD
